pysr3/__about__.py
pysr3/__init__.py
pysr3/logger.py
pysr3/priors.py
pysr3/regularizers.py
pysr3/solvers.py
pysr3/linear/__init__.py
pysr3/linear/models.py
pysr3/linear/oracles.py
pysr3/linear/problems.py
pysr3/lme/__init__.py
pysr3/lme/model_selectors.py
pysr3/lme/models.py
pysr3/lme/oracles.py
pysr3/lme/priors.py
pysr3/lme/problems.py
PySR3-0.3.5.dist-info/LICENSE
PySR3-0.3.5.dist-info/METADATA
PySR3-0.3.5.dist-info/WHEEL
PySR3-0.3.5.dist-info/top_level.txt
PySR3-0.3.5.dist-info/RECORD
